MANIFEST.in
README.md
setup.py
django_privatesite.egg-info/PKG-INFO
django_privatesite.egg-info/SOURCES.txt
django_privatesite.egg-info/dependency_links.txt
django_privatesite.egg-info/not-zip-safe
django_privatesite.egg-info/requires.txt
django_privatesite.egg-info/top_level.txt
privatesite/__init__.py
privatesite/admin.py
privatesite/models.py
privatesite/templates/admin/base_site.html
privatesite/templates/privatesite/base.html