Metadata-Version: 1.0
Name: django-privatesite
Version: 0.0.1
Summary: Django custom admins
Home-page: http://github.com/suvit/django-privatesite
Author: Victor Safronovich
Author-email: vsafronovich@gmail.com
License: MIT
Platform: UNKNOWN
